numba_scipy/__init__.py
numba_scipy/_version.py
numba_scipy/sparse.py
numba_scipy/special/__init__.py
numba_scipy/special/overloads.py
numba_scipy/special/signatures.py
numba_scipy/tests/__init__.py
numba_scipy/tests/test_sparse.py
numba_scipy/tests/test_special.py
numba_scipy-0.4.0.dist-info/LICENSE
numba_scipy-0.4.0.dist-info/METADATA
numba_scipy-0.4.0.dist-info/WHEEL
numba_scipy-0.4.0.dist-info/entry_points.txt
numba_scipy-0.4.0.dist-info/top_level.txt
numba_scipy-0.4.0.dist-info/RECORD
