Metadata-Version: 2.1
Name: numba-scipy
Version: 0.4.0
Summary: numba-scipy extends Numba to make it aware of SciPy
Home-page: https://github.com/numba/numba-scipy
Download-URL: https://github.com/numba/numba-scipy
Author: Anaconda, Inc.
Author-email: numba-users@continuum.io
License: BSD
Classifier: Development Status :: 3 - Alpha
Classifier: Intended Audience :: Developers
Classifier: License :: OSI Approved :: BSD License
Classifier: Operating System :: OS Independent
Classifier: Programming Language :: Python
Classifier: Programming Language :: Python :: 3.8
Classifier: Programming Language :: Python :: 3.9
Classifier: Programming Language :: Python :: 3.10
Classifier: Programming Language :: Python :: 3.11
Classifier: Topic :: Software Development :: Compilers
License-File: LICENSE
Requires-Dist: scipy <=1.11.0,>=0.16
Requires-Dist: numba >=0.45
